dynamic_parser/__init__.py
dynamic_parser/structure_json/__init__.py
dynamic_parser/structure_json/llm.py
dynamic_parser/structure_json/prompts.py
dynamic_parser/structure_json/utils.py
dynamic_parser-0.1.2.dist-info/LICENSE
dynamic_parser-0.1.2.dist-info/METADATA
dynamic_parser-0.1.2.dist-info/WHEEL
dynamic_parser-0.1.2.dist-info/top_level.txt
dynamic_parser-0.1.2.dist-info/RECORD
