Metadata-Version: 2.1
Name: dynamic-parser
Version: 0.1.2
Summary: Fix json structure and parse it
Home-page: https://github.com/ijaytelgote/dynamic_parser
Author: Jay Telgote
Author-email: ijaytelgote@gmail.com
License: MIT
Classifier: Programming Language :: Python :: 3
Classifier: License :: OSI Approved :: MIT License
Classifier: Operating System :: OS Independent
Requires-Python: >=3.9
License-File: LICENSE
Requires-Dist: langchain-groq
Requires-Dist: regex
Requires-Dist: pydantic
